CHANGES.txt
LICENSE.txt
MANIFEST.in
README.md
setup.py
GeobricksDBMS.egg-info/PKG-INFO
GeobricksDBMS.egg-info/SOURCES.txt
GeobricksDBMS.egg-info/dependency_links.txt
GeobricksDBMS.egg-info/requires.txt
GeobricksDBMS.egg-info/top_level.txt
geobricks_dbms/__init__.py
geobricks_dbms/__init__.pyc
geobricks_dbms/config/__init__.py
geobricks_dbms/config/__init__.pyc
geobricks_dbms/config/dbms_config.py
geobricks_dbms/config/dbms_config.pyc
geobricks_dbms/core/__init__.py
geobricks_dbms/core/__init__.pyc
geobricks_dbms/core/dbms_core.py
geobricks_dbms/core/dbms_core.pyc
geobricks_dbms/core/dbms_mongodb.py
geobricks_dbms/core/dbms_mongodb.pyc
geobricks_dbms/core/dbms_postgresql.py
geobricks_dbms/core/dbms_postgresql.pyc
geobricks_dbms/rest/__init__.py
geobricks_dbms/rest/__init__.pyc
geobricks_dbms/rest/dbms_rest.py
geobricks_dbms/rest/dbms_rest.pyc