Metadata-Version: 1.0
Name: GeobricksDBMS
Version: 0.1.5
Summary: Geobricks DB Management System.
Home-page: http://pypi.python.org/pypi/GeobricksDBMS/
Author: Simone Murzilli; Guido Barbaglia
Author-email: geobrickspy@gmail.com
License: LICENSE.txt
Platform: UNKNOWN
